{
  "n_models": 41,
  "n_with_permutation": 18,
  "n_with_native_shap": 27,
  "families": {
    "ARIMA": "other",
    "BayesianMCMC": "linear",
    "BayesianRidge": "linear",
    "CQR-LightGBM": "tree",
    "CQR-QuantReg": "other",
    "DLinear": "linear",
    "DNN": "dl",
    "DNN-Conformal": "other",
    "ElasticNet": "linear",
    "EpiEstim": "other",
    "FluSight-Baseline": "other",
    "FusedEpi": "other",
    "GAM-Spline": "other",
    "GAT": "dl",
    "GCN": "dl",
    "KRR": "kernel",
    "LightGBM": "other",
    "Mamba": "dl",
    "N-BEATS": "dl",
    "N-HiTS": "dl",
    "NegBinGLM": "linear",
    "OverseasTransfer": "dl",
    "PatchTST": "dl",
    "PoissonAutoreg": "linear",
    "RandomForest": "tree",
    "SARIMA": "other",
    "SARIMAX": "other",
    "SVR-Linear": "kernel",
    "SVR-RBF": "kernel",
    "SeirCount-TabPFN": "other",
    "TCN": "dl",
    "TabPFN": "other",
    "Theta": "other",
    "TiDE": "dl",
    "TiRex": "dl",
    "TimesFM-2.5": "other",
    "TimesNet": "dl",
    "Wallinga-Teunis": "other",
    "XGBoost": "tree",
    "hhh4-equivalent": "other",
    "iTransformer": "dl"
  },
  "mi_top10": [
    "ili_rate_lag1",
    "rt_subcrowd_ili",
    "bus_ili",
    "rt_highrisk_ili",
    "subway_ili",
    "rt_nonresnt_ili",
    "rt_roadcong_ili",
    "ili_rate_lag1_log1p",
    "ili_rate_lag1_qbin",
    "ili_rate_lag1_qnorm"
  ],
  "counting_rule": "a ranking counts as measured only if at least one attribution is non-zero (shap_analysis._measured); an all-zero result means the attribution could not be measured, not that every feature is irrelevant",
  "corrected": "scripts/correct_shap_report.py, 2026-07-19"
}